CHANGES.txt
DESCRIPTION.rst
LICENSE.txt
MANIFEST.in
README.txt
setup.cfg
setup.py
ConsumerCheck/ConsumerCheckLogo.png
ConsumerCheck/__init__.py
ConsumerCheck/about_consumercheck.py
ConsumerCheck/basic_stat_gui.py
ConsumerCheck/basic_stat_model.py
ConsumerCheck/cc_config.py
ConsumerCheck/cc_start.py
ConsumerCheck/combination_table.py
ConsumerCheck/conjoint_base.py
ConsumerCheck/conjoint_gui.py
ConsumerCheck/conjoint_machine.py
ConsumerCheck/conjoint_model.py
ConsumerCheck/cross_val.py
ConsumerCheck/dataset.py
ConsumerCheck/dataset_container.py
ConsumerCheck/dataset_matrix.py
ConsumerCheck/dialogs.py
ConsumerCheck/ds_matrix_view.py
ConsumerCheck/ds_slicer_view.py
ConsumerCheck/ds_table_view.py
ConsumerCheck/ds_ui.py
ConsumerCheck/exception_handler.py
ConsumerCheck/importer_file_base.py
ConsumerCheck/importer_interfaces.py
ConsumerCheck/importer_main.py
ConsumerCheck/importer_text_file.py
ConsumerCheck/importer_xls_file.py
ConsumerCheck/main_ui.py
ConsumerCheck/pca.py
ConsumerCheck/pca_gui.py
ConsumerCheck/pca_model.py
ConsumerCheck/pcr.py
ConsumerCheck/plot_base.py
ConsumerCheck/plot_conjoint.py
ConsumerCheck/plot_ev_line.py
ConsumerCheck/plot_histogram.py
ConsumerCheck/plot_interface.py
ConsumerCheck/plot_pc_scatter.py
ConsumerCheck/plot_sector.py
ConsumerCheck/plot_windows.py
ConsumerCheck/plscr_gui.py
ConsumerCheck/plscr_model.py
ConsumerCheck/plscr_picker.py
ConsumerCheck/plsr.py
ConsumerCheck/plugin_base.py
ConsumerCheck/plugin_tree_helper.py
ConsumerCheck/prefmap_gui.py
ConsumerCheck/prefmap_model.py
ConsumerCheck/prefmap_picker.py
ConsumerCheck/reset_xy.svg
ConsumerCheck/save.svg
ConsumerCheck/splash_screen.py
ConsumerCheck/statTools.py
ConsumerCheck/ui_results.py
ConsumerCheck/ui_results_new.py
ConsumerCheck/ui_tab_container_tree.py
ConsumerCheck/utilities.py
ConsumerCheck/window_helper.py
ConsumerCheck/x_down.svg
ConsumerCheck/x_up.svg
ConsumerCheck/y_down.svg
ConsumerCheck/y_up.svg
ConsumerCheck.egg-info/PKG-INFO
ConsumerCheck.egg-info/SOURCES.txt
ConsumerCheck.egg-info/dependency_links.txt
ConsumerCheck.egg-info/entry_points.txt
ConsumerCheck.egg-info/requires.txt
ConsumerCheck.egg-info/top_level.txt
ConsumerCheck/graphics/customer_attributes.ico
