Metadata-Version: 1.1
Name: ConsumerCheck
Version: 1.3.3
Summary: Software for analysis of sensory and consumer data
Home-page: http://sourceforge.net/projects/consumercheck/
Author: Oliver Tomic
Author-email: olivertomic@zoho.com
License: GNU GPLv3
Keywords: statistic education science
Platform: any
Classifier: Natural Language :: English
Classifier: Development Status :: 4 - Beta
Classifier: Programming Language :: Python :: 2.7
Classifier: Environment :: Win32 (MS Windows)
Classifier: Environment :: X11 Applications :: Qt
Classifier: Topic :: Scientific/Engineering
Classifier: Intended Audience :: Education
Classifier: Intended Audience :: End Users/Desktop
Classifier: Intended Audience :: Science/Research
Classifier: Operating System :: POSIX
Classifier: Operating System :: MacOS
Classifier: Operating System :: Microsoft :: Windows
Classifier: License :: OSI Approved :: GNU General Public License v3 or later (GPLv3+)
